{
	"brightnessRepeat": [
		{
			"id": "Default",
			"mirror": true,
			"values": {
				"0": 0,
				"1": 0,
				"2": 0,
				"3": 0,
				"4": 0,
				"5": 0,
				"6": 0,
				"7": 0,
				"8": 0,
				"9": 0,
				"10": 0,
				"11": 0,
				"12": 0,
				"13": 0,
				"14": 0,
				"15": 0,
				"16": 0,
				"17": 0,
				"18": 0,
				"19": 0,
				"20": 0,
				"21": 0,
				"22": 0,
				"23": 0,
				"24": 0,
				"25": 0,
				"26": 0,
				"27": 0,
				"28": 0,
				"29": 0,
				"30": 0,
				"31": 0,
				"32": 0,
				"33": 0,
				"34": 0,
				"35": 0,
				"36": 0,
				"37": 0,
				"38": 0,
				"39": 0,
				"40": 0,
				"41": 0,
				"42": 0,
				"43": 0,
				"44": 0,
				"45": 0,
				"46": 0,
				"47": 0,
				"48": 0,
				"49": 0,
				"50": 0,
				"51": 0,
				"52": 0,
				"53": 0,
				"54": 0,
				"55": 0,
				"56": 0,
				"57": 0,
				"58": 0,
				"59": 0,
				"60": 0,
				"61": 0,
				"62": 0,
				"63": 0,
				"64": 0,
				"65": 0,
				"66": 0,
				"67": 0,
				"68": 0,
				"69": 0,
				"70": 0,
				"71": 0,
				"72": 0,
				"73": 0,
				"74": 0,
				"75": 0,
				"76": 0,
				"77": 0,
				"78": 0,
				"79": 0,
				"80": 0,
				"81": 0,
				"82": 0,
				"83": 0,
				"84": 0,
				"85": 0,
				"86": 0,
				"87": 0,
				"88": 0,
				"89": 0,
				"90": 0,
				"91": 0,
				"92": 0,
				"93": 0,
				"94": 0,
				"95": 0
			}
		}
	],
	"columnTable": [
		{
			"id": "Default",
			"mirror": true,
			"values": {
				"0": {
					"repeat": 15,
					"time": 14
				},
				"1": {
					"repeat": 15,
					"time": 14
				},
				"2": {
					"repeat": 15,
					"time": 14
				},
				"3": {
					"repeat": 15,
					"time": 14
				},
				"4": {
					"repeat": 15,
					"time": 14
				},
				"5": {
					"repeat": 15,
					"time": 14
				},
				"6": {
					"repeat": 15,
					"time": 14
				},
				"7": {
					"repeat": 15,
					"time": 14
				},
				"8": {
					"repeat": 15,
					"time": 14
				},
				"9": {
					"repeat": 15,
					"time": 14
				},
				"10": {
					"repeat": 15,
					"time": 14
				},
				"11": {
					"repeat": 15,
					"time": 14
				},
				"12": {
					"repeat": 15,
					"time": 14
				},
				"13": {
					"repeat": 15,
					"time": 14
				},
				"14": {
					"repeat": 15,
					"time": 14
				},
				"15": {
					"repeat": 15,
					"time": 14
				},
				"16": {
					"repeat": 15,
					"time": 14
				},
				"17": {
					"repeat": 15,
					"time": 14
				},
				"18": {
					"repeat": 15,
					"time": 14
				},
				"19": {
					"repeat": 15,
					"time": 14
				},
				"20": {
					"repeat": 15,
					"time": 14
				},
				"21": {
					"repeat": 15,
					"time": 14
				},
				"22": {
					"repeat": 15,
					"time": 14
				},
				"23": {
					"repeat": 15,
					"time": 14
				},
				"24": {
					"repeat": 15,
					"time": 14
				},
				"25": {
					"repeat": 15,
					"time": 14
				},
				"26": {
					"repeat": 15,
					"time": 14
				},
				"27": {
					"repeat": 15,
					"time": 14
				},
				"28": {
					"repeat": 15,
					"time": 14
				},
				"29": {
					"repeat": 15,
					"time": 14
				},
				"30": {
					"repeat": 15,
					"time": 14
				},
				"31": {
					"repeat": 15,
					"time": 14
				},
				"32": {
					"repeat": 15,
					"time": 14
				},
				"33": {
					"repeat": 15,
					"time": 14
				},
				"34": {
					"repeat": 15,
					"time": 14
				},
				"35": {
					"repeat": 15,
					"time": 14
				},
				"36": {
					"repeat": 15,
					"time": 14
				},
				"37": {
					"repeat": 15,
					"time": 14
				},
				"38": {
					"repeat": 15,
					"time": 14
				},
				"39": {
					"repeat": 15,
					"time": 14
				},
				"40": {
					"repeat": 15,
					"time": 14
				},
				"41": {
					"repeat": 15,
					"time": 14
				},
				"42": {
					"repeat": 15,
					"time": 14
				},
				"43": {
					"repeat": 15,
					"time": 14
				},
				"44": {
					"repeat": 15,
					"time": 14
				},
				"45": {
					"repeat": 15,
					"time": 14
				},
				"46": {
					"repeat": 15,
					"time": 14
				},
				"47": {
					"repeat": 15,
					"time": 14
				},
				"48": {
					"repeat": 15,
					"time": 14
				},
				"49": {
					"repeat": 15,
					"time": 14
				},
				"50": {
					"repeat": 15,
					"time": 14
				},
				"51": {
					"repeat": 15,
					"time": 14
				},
				"52": {
					"repeat": 15,
					"time": 14
				},
				"53": {
					"repeat": 15,
					"time": 14
				},
				"54": {
					"repeat": 15,
					"time": 14
				},
				"55": {
					"repeat": 15,
					"time": 14
				},
				"56": {
					"repeat": 15,
					"time": 14
				},
				"57": {
					"repeat": 15,
					"time": 14
				},
				"58": {
					"repeat": 15,
					"time": 14
				},
				"59": {
					"repeat": 15,
					"time": 14
				},
				"60": {
					"repeat": 15,
					"time": 14
				},
				"61": {
					"repeat": 15,
					"time": 14
				},
				"62": {
					"repeat": 14,
					"time": 0
				},
				"63": {
					"repeat": 11,
					"time": 12
				},
				"64": {
					"repeat": 10,
					"time": 6
				},
				"65": {
					"repeat": 9,
					"time": 6
				},
				"66": {
					"repeat": 8,
					"time": 10
				},
				"67": {
					"repeat": 8,
					"time": 2
				},
				"68": {
					"repeat": 7,
					"time": 10
				},
				"69": {
					"repeat": 7,
					"time": 4
				},
				"70": {
					"repeat": 6,
					"time": 14
				},
				"71": {
					"repeat": 6,
					"time": 10
				},
				"72": {
					"repeat": 6,
					"time": 6
				},
				"73": {
					"repeat": 6,
					"time": 2
				},
				"74": {
					"repeat": 6,
					"time": 0
				},
				"75": {
					"repeat": 5,
					"time": 12
				},
				"76": {
					"repeat": 5,
					"time": 10
				},
				"77": {
					"repeat": 5,
					"time": 8
				},
				"78": {
					"repeat": 5,
					"time": 6
				},
				"79": {
					"repeat": 5,
					"time": 4
				},
				"80": {
					"repeat": 5,
					"time": 2
				},
				"81": {
					"repeat": 5,
					"time": 0
				},
				"82": {
					"repeat": 5,
					"time": 0
				},
				"83": {
					"repeat": 4,
					"time": 14
				},
				"84": {
					"repeat": 4,
					"time": 12
				},
				"85": {
					"repeat": 4,
					"time": 12
				},
				"86": {
					"repeat": 4,
					"time": 10
				},
				"87": {
					"repeat": 4,
					"time": 10
				},
				"88": {
					"repeat": 4,
					"time": 8
				},
				"89": {
					"repeat": 4,
					"time": 8
				},
				"90": {
					"repeat": 4,
					"time": 6
				},
				"91": {
					"repeat": 4,
					"time": 6
				},
				"92": {
					"repeat": 4,
					"time": 6
				},
				"93": {
					"repeat": 4,
					"time": 4
				},
				"94": {
					"repeat": 4,
					"time": 4
				},
				"95": {
					"repeat": 4,
					"time": 4
				},
				"96": {
					"repeat": 4,
					"time": 2
				},
				"97": {
					"repeat": 4,
					"time": 2
				},
				"98": {
					"repeat": 4,
					"time": 2
				},
				"99": {
					"repeat": 4,
					"time": 0
				},
				"100": {
					"repeat": 4,
					"time": 0
				},
				"101": {
					"repeat": 4,
					"time": 0
				},
				"102": {
					"repeat": 4,
					"time": 0
				},
				"103": {
					"repeat": 4,
					"time": 0
				},
				"104": {
					"repeat": 3,
					"time": 14
				},
				"105": {
					"repeat": 3,
					"time": 14
				},
				"106": {
					"repeat": 3,
					"time": 14
				},
				"107": {
					"repeat": 3,
					"time": 14
				},
				"108": {
					"repeat": 3,
					"time": 14
				},
				"109": {
					"repeat": 3,
					"time": 14
				},
				"110": {
					"repeat": 3,
					"time": 14
				},
				"111": {
					"repeat": 3,
					"time": 12
				},
				"112": {
					"repeat": 3,
					"time": 12
				},
				"113": {
					"repeat": 3,
					"time": 12
				},
				"114": {
					"repeat": 3,
					"time": 12
				},
				"115": {
					"repeat": 3,
					"time": 12
				},
				"116": {
					"repeat": 3,
					"time": 12
				},
				"117": {
					"repeat": 3,
					"time": 12
				},
				"118": {
					"repeat": 3,
					"time": 12
				},
				"119": {
					"repeat": 3,
					"time": 12
				},
				"120": {
					"repeat": 3,
					"time": 12
				},
				"121": {
					"repeat": 3,
					"time": 12
				},
				"122": {
					"repeat": 3,
					"time": 12
				},
				"123": {
					"repeat": 3,
					"time": 12
				},
				"124": {
					"repeat": 3,
					"time": 12
				},
				"125": {
					"repeat": 3,
					"time": 12
				},
				"126": {
					"repeat": 3,
					"time": 12
				},
				"127": {
					"repeat": 3,
					"time": 12
				},
				"128": {
					"repeat": 0,
					"time": 0
				},
				"129": {
					"repeat": 0,
					"time": 0
				},
				"130": {
					"repeat": 0,
					"time": 0
				},
				"131": {
					"repeat": 0,
					"time": 0
				},
				"132": {
					"repeat": 0,
					"time": 0
				},
				"133": {
					"repeat": 0,
					"time": 0
				},
				"134": {
					"repeat": 0,
					"time": 0
				},
				"135": {
					"repeat": 0,
					"time": 0
				},
				"136": {
					"repeat": 0,
					"time": 0
				},
				"137": {
					"repeat": 0,
					"time": 0
				},
				"138": {
					"repeat": 0,
					"time": 0
				},
				"139": {
					"repeat": 0,
					"time": 0
				},
				"140": {
					"repeat": 0,
					"time": 0
				},
				"141": {
					"repeat": 0,
					"time": 0
				},
				"142": {
					"repeat": 0,
					"time": 0
				},
				"143": {
					"repeat": 0,
					"time": 0
				},
				"144": {
					"repeat": 0,
					"time": 0
				},
				"145": {
					"repeat": 0,
					"time": 0
				},
				"146": {
					"repeat": 0,
					"time": 0
				},
				"147": {
					"repeat": 0,
					"time": 0
				},
				"148": {
					"repeat": 0,
					"time": 0
				},
				"149": {
					"repeat": 0,
					"time": 0
				},
				"150": {
					"repeat": 0,
					"time": 0
				},
				"151": {
					"repeat": 0,
					"time": 0
				},
				"152": {
					"repeat": 0,
					"time": 0
				},
				"153": {
					"repeat": 0,
					"time": 0
				},
				"154": {
					"repeat": 0,
					"time": 0
				},
				"155": {
					"repeat": 0,
					"time": 0
				},
				"156": {
					"repeat": 0,
					"time": 0
				},
				"157": {
					"repeat": 0,
					"time": 0
				},
				"158": {
					"repeat": 0,
					"time": 0
				},
				"159": {
					"repeat": 0,
					"time": 0
				},
				"160": {
					"repeat": 0,
					"time": 0
				},
				"161": {
					"repeat": 0,
					"time": 0
				},
				"162": {
					"repeat": 0,
					"time": 0
				},
				"163": {
					"repeat": 0,
					"time": 0
				},
				"164": {
					"repeat": 0,
					"time": 0
				},
				"165": {
					"repeat": 0,
					"time": 0
				},
				"166": {
					"repeat": 0,
					"time": 0
				},
				"167": {
					"repeat": 0,
					"time": 0
				},
				"168": {
					"repeat": 0,
					"time": 0
				},
				"169": {
					"repeat": 0,
					"time": 0
				},
				"170": {
					"repeat": 0,
					"time": 0
				},
				"171": {
					"repeat": 0,
					"time": 0
				},
				"172": {
					"repeat": 0,
					"time": 0
				},
				"173": {
					"repeat": 0,
					"time": 0
				},
				"174": {
					"repeat": 0,
					"time": 0
				},
				"175": {
					"repeat": 0,
					"time": 0
				},
				"176": {
					"repeat": 0,
					"time": 0
				},
				"177": {
					"repeat": 0,
					"time": 0
				},
				"178": {
					"repeat": 0,
					"time": 0
				},
				"179": {
					"repeat": 0,
					"time": 0
				},
				"180": {
					"repeat": 0,
					"time": 0
				},
				"181": {
					"repeat": 0,
					"time": 0
				},
				"182": {
					"repeat": 0,
					"time": 0
				},
				"183": {
					"repeat": 0,
					"time": 0
				},
				"184": {
					"repeat": 0,
					"time": 0
				},
				"185": {
					"repeat": 0,
					"time": 0
				},
				"186": {
					"repeat": 0,
					"time": 0
				},
				"187": {
					"repeat": 0,
					"time": 0
				},
				"188": {
					"repeat": 0,
					"time": 0
				},
				"189": {
					"repeat": 0,
					"time": 0
				},
				"190": {
					"repeat": 0,
					"time": 0
				},
				"191": {
					"repeat": 0,
					"time": 0
				},
				"192": {
					"repeat": 0,
					"time": 0
				},
				"193": {
					"repeat": 0,
					"time": 0
				},
				"194": {
					"repeat": 0,
					"time": 0
				},
				"195": {
					"repeat": 0,
					"time": 0
				},
				"196": {
					"repeat": 0,
					"time": 0
				},
				"197": {
					"repeat": 0,
					"time": 0
				},
				"198": {
					"repeat": 0,
					"time": 0
				},
				"199": {
					"repeat": 0,
					"time": 0
				},
				"200": {
					"repeat": 0,
					"time": 0
				},
				"201": {
					"repeat": 0,
					"time": 0
				},
				"202": {
					"repeat": 0,
					"time": 0
				},
				"203": {
					"repeat": 0,
					"time": 0
				},
				"204": {
					"repeat": 0,
					"time": 0
				},
				"205": {
					"repeat": 0,
					"time": 0
				},
				"206": {
					"repeat": 0,
					"time": 0
				},
				"207": {
					"repeat": 0,
					"time": 0
				},
				"208": {
					"repeat": 0,
					"time": 0
				},
				"209": {
					"repeat": 0,
					"time": 0
				},
				"210": {
					"repeat": 0,
					"time": 0
				},
				"211": {
					"repeat": 0,
					"time": 0
				},
				"212": {
					"repeat": 0,
					"time": 0
				},
				"213": {
					"repeat": 0,
					"time": 0
				},
				"214": {
					"repeat": 0,
					"time": 0
				},
				"215": {
					"repeat": 0,
					"time": 0
				},
				"216": {
					"repeat": 0,
					"time": 0
				},
				"217": {
					"repeat": 0,
					"time": 0
				},
				"218": {
					"repeat": 0,
					"time": 0
				},
				"219": {
					"repeat": 0,
					"time": 0
				},
				"220": {
					"repeat": 0,
					"time": 0
				},
				"221": {
					"repeat": 0,
					"time": 0
				},
				"222": {
					"repeat": 0,
					"time": 0
				},
				"223": {
					"repeat": 0,
					"time": 0
				},
				"224": {
					"repeat": 0,
					"time": 0
				},
				"225": {
					"repeat": 0,
					"time": 0
				},
				"226": {
					"repeat": 0,
					"time": 0
				},
				"227": {
					"repeat": 0,
					"time": 0
				},
				"228": {
					"repeat": 0,
					"time": 0
				},
				"229": {
					"repeat": 0,
					"time": 0
				},
				"230": {
					"repeat": 0,
					"time": 0
				},
				"231": {
					"repeat": 0,
					"time": 0
				},
				"232": {
					"repeat": 0,
					"time": 0
				},
				"233": {
					"repeat": 0,
					"time": 0
				},
				"234": {
					"repeat": 0,
					"time": 0
				},
				"235": {
					"repeat": 0,
					"time": 0
				},
				"236": {
					"repeat": 0,
					"time": 0
				},
				"237": {
					"repeat": 0,
					"time": 0
				},
				"238": {
					"repeat": 0,
					"time": 0
				},
				"239": {
					"repeat": 0,
					"time": 0
				},
				"240": {
					"repeat": 0,
					"time": 0
				},
				"241": {
					"repeat": 0,
					"time": 0
				},
				"242": {
					"repeat": 0,
					"time": 0
				},
				"243": {
					"repeat": 0,
					"time": 0
				},
				"244": {
					"repeat": 0,
					"time": 0
				},
				"245": {
					"repeat": 0,
					"time": 0
				},
				"246": {
					"repeat": 0,
					"time": 0
				},
				"247": {
					"repeat": 0,
					"time": 0
				},
				"248": {
					"repeat": 0,
					"time": 0
				},
				"249": {
					"repeat": 0,
					"time": 0
				},
				"250": {
					"repeat": 0,
					"time": 0
				},
				"251": {
					"repeat": 0,
					"time": 0
				},
				"252": {
					"repeat": 0,
					"time": 0
				},
				"253": {
					"repeat": 0,
					"time": 0
				},
				"254": {
					"repeat": 0,
					"time": 0
				},
				"255": {
					"repeat": 0,
					"time": 0
				}
			}
		}
	]
}